edwh_web2py_effdted_prio_grid/__about__.py
edwh_web2py_effdted_prio_grid/__init__.py
edwh_web2py_effdted_prio_grid-0.6.1.dist-info/METADATA
edwh_web2py_effdted_prio_grid-0.6.1.dist-info/WHEEL
edwh_web2py_effdted_prio_grid-0.6.1.dist-info/RECORD
