Metadata-Version: 2.3
Name: edwh-web2py-effdted-prio-grid
Version: 0.6.1
Summary: Web2py plugin for a effective dated grid with priority support.
Project-URL: Documentation, https://github.com/educationwarehouse/edwh-web2py-effdted-prio-grid#readme
Project-URL: Issues, https://github.com/educationwarehouse/edwh-web2py-effdted-prio-grid/issues
Project-URL: Source, https://github.com/educationwarehouse/edwh-web2py-effdted-prio-grid
Author-email: Remco Boerma <remco.b@educationwarehouse.nl>, Romy Schöller <romy.s@educationwarehouse.nl>, Robin van der Noord <robin.vdn@educationwarehouse.nl>
Keywords: effdt,effective-dated,grid,web2py
Classifier: Development Status :: 4 - Beta
Classifier: Programming Language :: Python
Classifier: Programming Language :: Python :: 3.10
Classifier: Programming Language :: Python :: 3.11
Classifier: Programming Language :: Python :: 3.12
Classifier: Programming Language :: Python :: Implementation :: CPython
Classifier: Programming Language :: Python :: Implementation :: PyPy
Requires-Python: >=3.10
Provides-Extra: dev
Requires-Dist: hatch; extra == 'dev'
Requires-Dist: python-semantic-release<8; extra == 'dev'
Requires-Dist: web2py-gluon; extra == 'dev'
